insarscript/__init__.py
insarscript/_version.py
insarscript/main.py
insarscript/core/__init__.py
insarscript/core/downloader.py
insarscript/core/processor.py
insarscript/core/sbas.py
insarscript/utils/__init__.py
insarscript/utils/addon.py
insarscript/utils/apis.py
insarscript/utils/tool.py
insarscript-1.0.0.post1.dist-info/licenses/LICENSE
insarscript-1.0.0.post1.dist-info/METADATA
insarscript-1.0.0.post1.dist-info/WHEEL
insarscript-1.0.0.post1.dist-info/top_level.txt
insarscript-1.0.0.post1.dist-info/RECORD
