Metadata-Version: 2.4
Name: insarscript
Version: 1.0.0.post1
Summary: Hassle-free InSAR processing scripts for multiple satellites
Author-email: jldz9 <Jiaweiliwork@outlook.com>
Project-URL: homepage, https://jldz9.github.io/InSARScript
Project-URL: repository, https://github.com/jldz9/InSARScript
Classifier: Programming Language :: Python :: 3
Classifier: Operating System :: OS Independent
Requires-Python: >=3.11
License-File: LICENSE
Requires-Dist: asf_search
Requires-Dist: colorama
Requires-Dist: contextily
Requires-Dist: dem_stitcher
Requires-Dist: hyp3_sdk
Requires-Dist: matplotlib
Requires-Dist: mintpy
Requires-Dist: python_box
Requires-Dist: rasterio>1.4
Requires-Dist: sentineleof
Requires-Dist: tomli_w
Dynamic: license-file
